<?xml version="1.0" encoding="UTF-8"?>
<objects serializationModel="Studio.02.02.00">
	<object class="AudioFile" id="{0b4c8696-fdbc-493d-8f69-5257cfd94a1f}">
		<property name="assetPath">
			<value>SFX/Objects/Door/door_break.wav</value>
		</property>
		<property name="frequencyInKHz">
			<value>44.0999985</value>
		</property>
		<property name="channelCount">
			<value>2</value>
		</property>
		<property name="length">
			<value>2.9518367346938774</value>
		</property>
		<relationship name="masterAssetFolder">
			<destination>{ea1368a2-101b-4477-9436-7a8455276d35}</destination>
		</relationship>
	</object>
</objects>
